tothemoon/__init__.py
tothemoon/btc_model.h5
tothemoon/btclogscaler.gz
tothemoon/moon.py
tothemoon/test.py
tothemoon-0.1.9.dist-info/LICENSE
tothemoon-0.1.9.dist-info/METADATA
tothemoon-0.1.9.dist-info/WHEEL
tothemoon-0.1.9.dist-info/top_level.txt
tothemoon-0.1.9.dist-info/RECORD
